{
    "Information Security": {
        "ML-KEM": {
            "NL": "ntb",
            "EN": "Lattice-based. Based on the learning with errors problem in structured (module) lattices"
        },
        "Classic McEliece": {
            "NL": "ntb",
            "EN": "Code-based. Based on the decoding of Goppa codes"
        },
        "FrodoKEM": {
            "NL": "ntb",
            "EN": "Lattice-based. Based on the learning with errors problem in unstructured lattices"
        },
        "HQC": {
            "NL": "ntb",
            "EN": "Code-based. Based on quasi-cyclic moderate density parity-check"
        },
        "BIKE": {
            "NL": "ntb",
            "EN": "Code-based. Based on the Syndrome Decoding problem"
        }
    },
    "Maturity": {
        "ML-KEM": {
            "NL": "ntb",
            "EN": "Published in 2017"
        },
        "Classic McEliece": {
            "NL": "ntb",
            "EN": "Most mature algorithm, in use for over 40 years"
        },
        "FrodoKEM": {
            "NL": "ntb",
            "EN": "Published in 2016"
        },
        "HQC": {
            "NL": "ntb",
            "EN": "Published in 2017"
        },
        "BIKE": {
            "NL": "ntb",
            "EN": "Published in 2018"
        }
    },
    "Standardisation": {
        "ML-KEM": {
            "NL": "ntb",
            "EN": "Won NIST's six-year long competition and was selected as its main standard in 2024"
        },
        "Classic McEliece": {
            "NL": "ntb",
            "EN": "Still in competition - has been selected for NIST standardization round 4"
        },
        "FrodoKEM": {
            "NL": "ntb",
            "EN": "Selected as an alternate candidate by NIST, but not selected for standardization"
        },
        "HQC": {
            "NL": "ntb",
            "EN": "Still in competition - has been selected for NIST standardization round 4"
        },
        "BIKE": {
            "NL": "ntb",
            "EN": "Still in competition - has been selected for NIST standardization round 4"
        }
    },
    "Hardware": {
        "ML-KEM": {
            "NL": "ntb",
            "EN": "Integrated in ARM Cortex A, M53, M4(F), M0+; FPGA, ASIC, SLE 78, RISC-V"
        },
        "Classic McEliece": {
            "NL": "ntb",
            "EN": "Integrated in ARM Cortex M4, FPGA"
        },
        "FrodoKEM": {
            "NL": "ntb",
            "EN": "Integrated in ARM Cortex M4, Xilinx Artix-7, ASIC, RISC-V"
        },
        "HQC": {
            "NL": "ntb",
            "EN": "Integrated in Xilinx Artix-7 FPGA"
        },
        "BIKE": {
            "NL": "ntb",
            "EN": "Integrated in VHDL for Xilinx FPGA"
        }
    },
    "Storage & communication": {
        "ML-KEM": {
            "NL": "ntb",
            "EN": "Very small keys, relatively small ciphertexts"
        },
        "Classic McEliece": {
            "NL": "ntb",
            "EN": "Extremely large public keys, but smallest ciphertexts"
        },
        "FrodoKEM": {
            "NL": "ntb",
            "EN": "Very large ciphertexts, relatively large keys"
        },
        "HQC": {
            "NL": "ntb",
            "EN": "Small keys, but large ciphertexts"
        },
        "BIKE": {
            "NL": "ntb",
            "EN": "Small keys, fairly small ciphertexts"
        }
    },
    "Performance": {
        "ML-KEM": {
            "NL": "ntb",
            "EN": "Fastest key generation, encryption and decryption"
        },
        "Classic McEliece": {
            "NL": "ntb",
            "EN": "Extremely slow key generation, but very fast encryption and decryption"
        },
        "FrodoKEM": {
            "NL": "ntb",
            "EN": "Very slow encryption, relatively slow decryption and key generation"
        },
        "HQC": {
            "NL": "ntb",
            "EN": "Very fast key generation, also fast encryption and decryption"
        },
        "BIKE": {
            "NL": "ntb",
            "EN": "Fairly fast key generation, very fast encryption but slower decryption"
        }
    },
    "Sizes (NIST level 1)": {
        "ML-KEM": {
            "NL": "ntb",
            "EN": "Public key: 0.8 kB, secret key: 1.6 kB, ciphertext: 0.8 kB"
        },
        "Classic McEliece": {
            "NL": "ntb",
            "EN": "Public key: 261 kB, secret key: 6.5 kB, ciphertext: 0.1 kB"
        },
        "FrodoKEM": {
            "NL": "ntb",
            "EN": "Public key: 9.6 kB, secret key: 20 kB, ciphertext: 9.8 kB"
        },
        "HQC": {
            "NL": "ntb",
            "EN": "Public key: 3.0 kB, secret key: 3.0 kB, ciphertext: 6.0 kB"
        },
        "BIKE": {
            "NL": "ntb",
            "EN": "Public key: 1.5 kB, secret key: 5.2 kB, ciphertext: 1.6 kB"
        }
    },
    "Side channel attack countermeasures": {
        "ML-KEM": {
            "NL": "ntb",
            "EN": "tbd"
        },
        "Classic McEliece": {
            "NL": "ntb",
            "EN": "tbd"
        },
        "FrodoKEM": {
            "NL": "ntb",
            "EN": "tbd"
        },
        "HQC": {
            "NL": "ntb",
            "EN": "tbd"
        },
        "BIKE": {
            "NL": "ntb",
            "EN": "tbd"
        }
    },
    "Key issues": {
        "ML-KEM": {
            "NL": "-",
            "EN": "-"
        },
        "Classic McEliece": {
            "NL": "-",
            "EN": "-"
        },
        "FrodoKEM": {
            "NL": "-",
            "EN": "-"
        },
        "HQC": {
            "NL": "-",
            "EN": "-"
        },
        "BIKE": {
            "NL": "-",
            "EN": "Has possible decryption failures, related to performance"
        }
    }
}